ast_magic/__init__.py
ast_magic-1.0.1.dist-info/METADATA
ast_magic-1.0.1.dist-info/WHEEL
ast_magic-1.0.1.dist-info/top_level.txt
ast_magic-1.0.1.dist-info/RECORD
